corefeval/__init__.py
corefeval/__main__.py
corefeval/document.py
corefeval/evaluation.py
corefeval/metric.py
corefeval/scorer.py
corefeval/metrics/__init__.py
corefeval/metrics/_b_cubed.py
corefeval/metrics/_ceafe.py
corefeval/metrics/_lea.py
corefeval/metrics/_muc.py
corefeval/utils/__init__.py
corefeval/utils/coref_types.py
corefeval/utils/linear_assignment.py
coreference_eval-0.0.2.dist-info/LICENSE
coreference_eval-0.0.2.dist-info/METADATA
coreference_eval-0.0.2.dist-info/WHEEL
coreference_eval-0.0.2.dist-info/top_level.txt
coreference_eval-0.0.2.dist-info/RECORD
