Metadata-Version: 2.1
Name: coreference-eval
Version: 0.0.2
Summary: Common metrics and evaluation tools for coreference chains (jsonline format)
Home-page: https://github.com/tollefj/coreference-eval
Author: tollef jørgensen
Author-email: tollefj@gmail.com
Classifier: Programming Language :: Python :: 3
Classifier: License :: OSI Approved :: MIT License
Classifier: Operating System :: OS Independent
Requires-Python: >=3.9
License-File: LICENSE
